Metadata-Version: 2.1
Name: pyduckduckgosearch
Version: 1.2.1
Summary: A Python library for scraping the DuckDuckGo search engine.
Home-page: https://github.com/adahirwar/websearch
Author: Arvind Ahirwar
Author-email: ad.ahirwar@gmail.com
License: UNKNOWN
Platform: UNKNOWN
Classifier: Programming Language :: Python :: 3
Classifier: License :: OSI Approved :: MIT License
Classifier: Operating System :: OS Independent
Requires-Python: >=3.6
License-File: LICENSE
